{"file:///c%3A/Workspaces/Visual%20Studio%20Code/wuye/sp-ic-b/.eslintrc.js":{"language":"JavaScript","code":25,"comment":0,"blank":1},"file:///c%3A/Workspaces/Visual%20Studio%20Code/wuye/sp-ic-b/package.json":{"language":"JSON","code":73,"comment":0,"blank":1},"file:///c%3A/Workspaces/Visual%20Studio%20Code/wuye/sp-ic-b/README.md":{"language":"Markdown","code":51,"comment":2,"blank":21},"file:///c%3A/Workspaces/Visual%20Studio%20Code/wuye/sp-ic-b/tsconfig.build.json":{"language":"JSON","code":4,"comment":0,"blank":1},"file:///c%3A/Workspaces/Visual%20Studio%20Code/wuye/sp-ic-b/src/message/message.service.ts":{"language":"TypeScript","code":48,"comment":0,"blank":12},"file:///c%3A/Workspaces/Visual%20Studio%20Code/wuye/sp-ic-b/src/message/message.service.spec.ts":{"language":"TypeScript","code":14,"comment":0,"blank":5},"file:///c%3A/Workspaces/Visual%20Studio%20Code/wuye/sp-ic-b/src/store/store.service.ts":{"language":"TypeScript","code":73,"comment":0,"blank":16},"file:///c%3A/Workspaces/Visual%20Studio%20Code/wuye/sp-ic-b/src/store/store.service.spec.ts":{"language":"TypeScript","code":14,"comment":0,"blank":5},"file:///c%3A/Workspaces/Visual%20Studio%20Code/wuye/sp-ic-b/src/store/store.module.ts":{"language":"TypeScript","code":11,"comment":0,"blank":2},"file:///c%3A/Workspaces/Visual%20Studio%20Code/wuye/sp-ic-b/src/store/store.controller.ts":{"language":"TypeScript","code":57,"comment":0,"blank":10},"file:///c%3A/Workspaces/Visual%20Studio%20Code/wuye/sp-ic-b/src/store/store.controller.spec.ts":{"language":"TypeScript","code":16,"comment":0,"blank":5},"file:///c%3A/Workspaces/Visual%20Studio%20Code/wuye/sp-ic-b/src/notice/notice.service.ts":{"language":"TypeScript","code":51,"comment":1,"blank":14},"file:///c%3A/Workspaces/Visual%20Studio%20Code/wuye/sp-ic-b/src/notice/notice.service.spec.ts":{"language":"TypeScript","code":14,"comment":0,"blank":5},"file:///c%3A/Workspaces/Visual%20Studio%20Code/wuye/sp-ic-b/src/user/user.service.ts":{"language":"TypeScript","code":168,"comment":0,"blank":38},"file:///c%3A/Workspaces/Visual%20Studio%20Code/wuye/sp-ic-b/src/store/entities/store.entity.ts":{"language":"TypeScript","code":26,"comment":0,"blank":11},"file:///c%3A/Workspaces/Visual%20Studio%20Code/wuye/sp-ic-b/src/user/user.service.spec.ts":{"language":"TypeScript","code":14,"comment":0,"blank":5},"file:///c%3A/Workspaces/Visual%20Studio%20Code/wuye/sp-ic-b/src/notice/notice.module.ts":{"language":"TypeScript","code":11,"comment":0,"blank":2},"file:///c%3A/Workspaces/Visual%20Studio%20Code/wuye/sp-ic-b/src/user/user.module.ts":{"language":"TypeScript","code":11,"comment":0,"blank":2},"file:///c%3A/Workspaces/Visual%20Studio%20Code/wuye/sp-ic-b/src/notice/notice.controller.ts":{"language":"TypeScript","code":49,"comment":0,"blank":10},"file:///c%3A/Workspaces/Visual%20Studio%20Code/wuye/sp-ic-b/tsconfig.json":{"language":"JSON with Comments","code":22,"comment":0,"blank":0},"file:///c%3A/Workspaces/Visual%20Studio%20Code/wuye/sp-ic-b/src/notice/notice.controller.spec.ts":{"language":"TypeScript","code":16,"comment":0,"blank":5},"file:///c%3A/Workspaces/Visual%20Studio%20Code/wuye/sp-ic-b/src/user/user.controller.ts":{"language":"TypeScript","code":147,"comment":0,"blank":26},"file:///c%3A/Workspaces/Visual%20Studio%20Code/wuye/sp-ic-b/src/user/dtos/user.delete.dto.ts":{"language":"TypeScript","code":6,"comment":0,"blank":1},"file:///c%3A/Workspaces/Visual%20Studio%20Code/wuye/sp-ic-b/src/user/dtos/user.query.dto.ts":{"language":"TypeScript","code":7,"comment":0,"blank":2},"file:///c%3A/Workspaces/Visual%20Studio%20Code/wuye/sp-ic-b/src/user/dtos/user.login.dto.ts":{"language":"TypeScript","code":4,"comment":0,"blank":1},"file:///c%3A/Workspaces/Visual%20Studio%20Code/wuye/sp-ic-b/src/user/dtos/user.create.dto.ts":{"language":"TypeScript","code":15,"comment":0,"blank":10},"file:///c%3A/Workspaces/Visual%20Studio%20Code/wuye/sp-ic-b/src/user/dtos/user.ban_talk.dto.ts":{"language":"TypeScript","code":7,"comment":0,"blank":2},"file:///c%3A/Workspaces/Visual%20Studio%20Code/wuye/sp-ic-b/src/user/user.controller.spec.ts":{"language":"TypeScript","code":16,"comment":0,"blank":5},"file:///c%3A/Workspaces/Visual%20Studio%20Code/wuye/sp-ic-b/src/user/dtos/user.reset_password_own.dto.ts":{"language":"TypeScript","code":7,"comment":0,"blank":2},"file:///c%3A/Workspaces/Visual%20Studio%20Code/wuye/sp-ic-b/src/user/dtos/user.update.dto.ts":{"language":"TypeScript","code":18,"comment":0,"blank":13},"file:///c%3A/Workspaces/Visual%20Studio%20Code/wuye/sp-ic-b/src/notice/entities/notice.entity.ts":{"language":"TypeScript","code":22,"comment":0,"blank":9},"file:///c%3A/Workspaces/Visual%20Studio%20Code/wuye/sp-ic-b/src/user/dtos/user.upload_head_img.dto.ts":{"language":"TypeScript","code":6,"comment":0,"blank":1},"file:///c%3A/Workspaces/Visual%20Studio%20Code/wuye/sp-ic-b/src/user/dtos/user.update_own.dto.ts":{"language":"TypeScript","code":8,"comment":0,"blank":3},"file:///c%3A/Workspaces/Visual%20Studio%20Code/wuye/sp-ic-b/src/user/dtos/user.reset_password_admin.dto.ts":{"language":"TypeScript","code":6,"comment":0,"blank":1},"file:///c%3A/Workspaces/Visual%20Studio%20Code/wuye/sp-ic-b/src/user/dtos/user.register.dto.ts":{"language":"TypeScript","code":10,"comment":0,"blank":7},"file:///c%3A/Workspaces/Visual%20Studio%20Code/wuye/sp-ic-b/src/store/dtos/store.query.dto.ts":{"language":"TypeScript","code":8,"comment":0,"blank":3},"file:///c%3A/Workspaces/Visual%20Studio%20Code/wuye/sp-ic-b/src/store/dtos/store.delete.dto.ts":{"language":"TypeScript","code":6,"comment":0,"blank":1},"file:///c%3A/Workspaces/Visual%20Studio%20Code/wuye/sp-ic-b/src/message/message.controller.ts":{"language":"TypeScript","code":38,"comment":0,"blank":9},"file:///c%3A/Workspaces/Visual%20Studio%20Code/wuye/sp-ic-b/src/message/message.module.ts":{"language":"TypeScript","code":11,"comment":0,"blank":2},"file:///c%3A/Workspaces/Visual%20Studio%20Code/wuye/sp-ic-b/src/store/dtos/store.create.dto.ts":{"language":"TypeScript","code":12,"comment":0,"blank":7},"file:///c%3A/Workspaces/Visual%20Studio%20Code/wuye/sp-ic-b/src/message/message.controller.spec.ts":{"language":"TypeScript","code":16,"comment":0,"blank":5},"file:///c%3A/Workspaces/Visual%20Studio%20Code/wuye/sp-ic-b/src/store/dtos/store.update.dto.ts":{"language":"TypeScript","code":12,"comment":0,"blank":7},"file:///c%3A/Workspaces/Visual%20Studio%20Code/wuye/sp-ic-b/src/message/dtos/message.read.dto.ts":{"language":"TypeScript","code":6,"comment":0,"blank":1},"file:///c%3A/Workspaces/Visual%20Studio%20Code/wuye/sp-ic-b/src/user/entities/user.entity.ts":{"language":"TypeScript","code":44,"comment":0,"blank":20},"file:///c%3A/Workspaces/Visual%20Studio%20Code/wuye/sp-ic-b/src/message/dtos/message.query.dto.ts":{"language":"TypeScript","code":7,"comment":0,"blank":2},"file:///c%3A/Workspaces/Visual%20Studio%20Code/wuye/sp-ic-b/src/message/entities/message.entity.ts":{"language":"TypeScript","code":20,"comment":0,"blank":8},"file:///c%3A/Workspaces/Visual%20Studio%20Code/wuye/sp-ic-b/src/message/dtos/message.create.dto.ts":{"language":"TypeScript","code":9,"comment":0,"blank":4},"file:///c%3A/Workspaces/Visual%20Studio%20Code/wuye/sp-ic-b/src/notice/dtos/notice.update.dto.ts":{"language":"TypeScript","code":9,"comment":0,"blank":4},"file:///c%3A/Workspaces/Visual%20Studio%20Code/wuye/sp-ic-b/src/notice/dtos/notice.query.dto.ts":{"language":"TypeScript","code":7,"comment":0,"blank":2},"file:///c%3A/Workspaces/Visual%20Studio%20Code/wuye/sp-ic-b/src/notice/dtos/notice.delete.dto.ts":{"language":"TypeScript","code":6,"comment":0,"blank":1},"file:///c%3A/Workspaces/Visual%20Studio%20Code/wuye/sp-ic-b/src/notice/dtos/notice.create.dto.ts":{"language":"TypeScript","code":9,"comment":0,"blank":4},"file:///c%3A/Workspaces/Visual%20Studio%20Code/wuye/sp-ic-b/src/post_like/post_like.controller.spec.ts":{"language":"TypeScript","code":16,"comment":0,"blank":5},"file:///c%3A/Workspaces/Visual%20Studio%20Code/wuye/sp-ic-b/src/post_comment_like/post_comment_like.service.spec.ts":{"language":"TypeScript","code":14,"comment":0,"blank":5},"file:///c%3A/Workspaces/Visual%20Studio%20Code/wuye/sp-ic-b/src/post_comment_like/post_comment_like.module.ts":{"language":"TypeScript","code":11,"comment":0,"blank":2},"file:///c%3A/Workspaces/Visual%20Studio%20Code/wuye/sp-ic-b/src/power/power.service.ts":{"language":"TypeScript","code":34,"comment":0,"blank":7},"file:///c%3A/Workspaces/Visual%20Studio%20Code/wuye/sp-ic-b/src/post_comment_like/post_comment_like.service.ts":{"language":"TypeScript","code":49,"comment":0,"blank":11},"file:///c%3A/Workspaces/Visual%20Studio%20Code/wuye/sp-ic-b/src/repair/repair.service.ts":{"language":"TypeScript","code":63,"comment":1,"blank":14},"file:///c%3A/Workspaces/Visual%20Studio%20Code/wuye/sp-ic-b/src/power/entities/power.entity.ts":{"language":"TypeScript","code":48,"comment":0,"blank":22},"file:///c%3A/Workspaces/Visual%20Studio%20Code/wuye/sp-ic-b/src/repair/repair.service.spec.ts":{"language":"TypeScript","code":14,"comment":0,"blank":5},"file:///c%3A/Workspaces/Visual%20Studio%20Code/wuye/sp-ic-b/src/post_comment/post_comment.service.spec.ts":{"language":"TypeScript","code":14,"comment":0,"blank":5},"file:///c%3A/Workspaces/Visual%20Studio%20Code/wuye/sp-ic-b/src/post_comment/dtos/post_comment.delete.dto.ts":{"language":"TypeScript","code":6,"comment":0,"blank":1},"file:///c%3A/Workspaces/Visual%20Studio%20Code/wuye/sp-ic-b/src/post_comment/post_comment.service.ts":{"language":"TypeScript","code":66,"comment":0,"blank":12},"file:///c%3A/Workspaces/Visual%20Studio%20Code/wuye/sp-ic-b/src/post_comment/post_comment.controller.ts":{"language":"TypeScript","code":40,"comment":0,"blank":8},"file:///c%3A/Workspaces/Visual%20Studio%20Code/wuye/sp-ic-b/src/post_comment/dtos/post_comment.query.dto.ts":{"language":"TypeScript","code":8,"comment":0,"blank":3},"file:///c%3A/Workspaces/Visual%20Studio%20Code/wuye/sp-ic-b/src/post_comment/dtos/post_comment.create.dto.ts":{"language":"TypeScript","code":9,"comment":0,"blank":4},"file:///c%3A/Workspaces/Visual%20Studio%20Code/wuye/sp-ic-b/src/post_comment/post_comment.controller.spec.ts":{"language":"TypeScript","code":16,"comment":0,"blank":5},"file:///c%3A/Workspaces/Visual%20Studio%20Code/wuye/sp-ic-b/src/power/power.service.spec.ts":{"language":"TypeScript","code":14,"comment":0,"blank":5},"file:///c%3A/Workspaces/Visual%20Studio%20Code/wuye/sp-ic-b/src/post_like/post_like.service.ts":{"language":"TypeScript","code":48,"comment":0,"blank":11},"file:///c%3A/Workspaces/Visual%20Studio%20Code/wuye/sp-ic-b/src/repair/repair.controller.ts":{"language":"TypeScript","code":47,"comment":0,"blank":10},"file:///c%3A/Workspaces/Visual%20Studio%20Code/wuye/sp-ic-b/src/post_comment/post_comment.module.ts":{"language":"TypeScript","code":11,"comment":0,"blank":2},"file:///c%3A/Workspaces/Visual%20Studio%20Code/wuye/sp-ic-b/src/post_comment_like/post_comment_like.controller.ts":{"language":"TypeScript","code":34,"comment":0,"blank":8},"file:///c%3A/Workspaces/Visual%20Studio%20Code/wuye/sp-ic-b/src/post_like/post_like.service.spec.ts":{"language":"TypeScript","code":14,"comment":0,"blank":5},"file:///c%3A/Workspaces/Visual%20Studio%20Code/wuye/sp-ic-b/src/power/power.module.ts":{"language":"TypeScript","code":11,"comment":0,"blank":2},"file:///c%3A/Workspaces/Visual%20Studio%20Code/wuye/sp-ic-b/src/repair/repair.controller.spec.ts":{"language":"TypeScript","code":16,"comment":0,"blank":5},"file:///c%3A/Workspaces/Visual%20Studio%20Code/wuye/sp-ic-b/src/post_comment_like/post_comment_like.controller.spec.ts":{"language":"TypeScript","code":16,"comment":0,"blank":5},"file:///c%3A/Workspaces/Visual%20Studio%20Code/wuye/sp-ic-b/src/power/power.controller.ts":{"language":"TypeScript","code":14,"comment":0,"blank":4},"file:///c%3A/Workspaces/Visual%20Studio%20Code/wuye/sp-ic-b/src/post_like/post_like.module.ts":{"language":"TypeScript","code":11,"comment":0,"blank":2},"file:///c%3A/Workspaces/Visual%20Studio%20Code/wuye/sp-ic-b/src/power/power.controller.spec.ts":{"language":"TypeScript","code":16,"comment":0,"blank":5},"file:///c%3A/Workspaces/Visual%20Studio%20Code/wuye/sp-ic-b/src/repair/dtos/repair.create.dto.ts":{"language":"TypeScript","code":9,"comment":0,"blank":4},"file:///c%3A/Workspaces/Visual%20Studio%20Code/wuye/sp-ic-b/src/post_like/post_like.controller.ts":{"language":"TypeScript","code":34,"comment":0,"blank":8},"file:///c%3A/Workspaces/Visual%20Studio%20Code/wuye/sp-ic-b/src/repair/dtos/repair.query.dto.ts":{"language":"TypeScript","code":7,"comment":0,"blank":2},"file:///c%3A/Workspaces/Visual%20Studio%20Code/wuye/sp-ic-b/src/repair/dtos/repair.delete.dto.ts":{"language":"TypeScript","code":6,"comment":0,"blank":1},"file:///c%3A/Workspaces/Visual%20Studio%20Code/wuye/sp-ic-b/src/repair/entities/repair.entity.ts":{"language":"TypeScript","code":20,"comment":0,"blank":8},"file:///c%3A/Workspaces/Visual%20Studio%20Code/wuye/sp-ic-b/src/post_comment/entities/post_comment.entity.ts":{"language":"TypeScript","code":23,"comment":0,"blank":9},"file:///c%3A/Workspaces/Visual%20Studio%20Code/wuye/sp-ic-b/src/post_comment_like/entities/post_comment_like.entity.ts":{"language":"TypeScript","code":14,"comment":0,"blank":5},"file:///c%3A/Workspaces/Visual%20Studio%20Code/wuye/sp-ic-b/src/post_comment_like/dtos/post_comment_like.query.ts":{"language":"TypeScript","code":6,"comment":0,"blank":1},"file:///c%3A/Workspaces/Visual%20Studio%20Code/wuye/sp-ic-b/src/repair/repair.module.ts":{"language":"TypeScript","code":11,"comment":0,"blank":2},"file:///c%3A/Workspaces/Visual%20Studio%20Code/wuye/sp-ic-b/src/post_comment_like/dtos/post_comment_like.delete.ts":{"language":"TypeScript","code":6,"comment":0,"blank":1},"file:///c%3A/Workspaces/Visual%20Studio%20Code/wuye/sp-ic-b/src/power/dtos/power.query.dto.ts":{"language":"TypeScript","code":2,"comment":0,"blank":1},"file:///c%3A/Workspaces/Visual%20Studio%20Code/wuye/sp-ic-b/src/post_comment_like/dtos/post_comment_like.create.dto.ts":{"language":"TypeScript","code":7,"comment":0,"blank":2},"file:///c%3A/Workspaces/Visual%20Studio%20Code/wuye/sp-ic-b/src/post_like/entities/post_like.entity.ts":{"language":"TypeScript","code":14,"comment":0,"blank":5},"file:///c%3A/Workspaces/Visual%20Studio%20Code/wuye/sp-ic-b/src/post/post.module.ts":{"language":"TypeScript","code":11,"comment":0,"blank":2},"file:///c%3A/Workspaces/Visual%20Studio%20Code/wuye/sp-ic-b/src/post/post.controller.ts":{"language":"TypeScript","code":52,"comment":0,"blank":10},"file:///c%3A/Workspaces/Visual%20Studio%20Code/wuye/sp-ic-b/src/repair/dtos/repair.update.dto.ts":{"language":"TypeScript","code":7,"comment":0,"blank":2},"file:///c%3A/Workspaces/Visual%20Studio%20Code/wuye/sp-ic-b/src/post/post.controller.spec.ts":{"language":"TypeScript","code":16,"comment":0,"blank":5},"file:///c%3A/Workspaces/Visual%20Studio%20Code/wuye/sp-ic-b/src/post_collect/post_collect.module.ts":{"language":"TypeScript","code":11,"comment":0,"blank":2},"file:///c%3A/Workspaces/Visual%20Studio%20Code/wuye/sp-ic-b/src/post/dtos/post.update.dto.ts":{"language":"TypeScript","code":7,"comment":0,"blank":2},"file:///c%3A/Workspaces/Visual%20Studio%20Code/wuye/sp-ic-b/src/post_collect/post_collect.controller.ts":{"language":"TypeScript","code":45,"comment":0,"blank":10},"file:///c%3A/Workspaces/Visual%20Studio%20Code/wuye/sp-ic-b/src/post/entities/post.entity.ts":{"language":"TypeScript","code":28,"comment":0,"blank":12},"file:///c%3A/Workspaces/Visual%20Studio%20Code/wuye/sp-ic-b/src/post/dtos/post.query.dto.ts":{"language":"TypeScript","code":8,"comment":0,"blank":3},"file:///c%3A/Workspaces/Visual%20Studio%20Code/wuye/sp-ic-b/src/post/dtos/post.delete.dto.ts":{"language":"TypeScript","code":6,"comment":0,"blank":1},"file:///c%3A/Workspaces/Visual%20Studio%20Code/wuye/sp-ic-b/src/post_collect/post_collect.controller.spec.ts":{"language":"TypeScript","code":16,"comment":0,"blank":5},"file:///c%3A/Workspaces/Visual%20Studio%20Code/wuye/sp-ic-b/src/post_collect/post_collect.service.ts":{"language":"TypeScript","code":75,"comment":0,"blank":14},"file:///c%3A/Workspaces/Visual%20Studio%20Code/wuye/sp-ic-b/src/outsider/outsider.service.ts":{"language":"TypeScript","code":47,"comment":0,"blank":14},"file:///c%3A/Workspaces/Visual%20Studio%20Code/wuye/sp-ic-b/src/post_collect/post_collect.service.spec.ts":{"language":"TypeScript","code":14,"comment":0,"blank":5},"file:///c%3A/Workspaces/Visual%20Studio%20Code/wuye/sp-ic-b/src/post/dtos/post.create.dto.ts":{"language":"TypeScript","code":11,"comment":0,"blank":6},"file:///c%3A/Workspaces/Visual%20Studio%20Code/wuye/sp-ic-b/src/payment/entities/payment.entity.ts":{"language":"TypeScript","code":26,"comment":0,"blank":11},"file:///c%3A/Workspaces/Visual%20Studio%20Code/wuye/sp-ic-b/src/parking/parking.service.ts":{"language":"TypeScript","code":68,"comment":0,"blank":15},"file:///c%3A/Workspaces/Visual%20Studio%20Code/wuye/sp-ic-b/src/outsider/outsider.service.spec.ts":{"language":"TypeScript","code":14,"comment":0,"blank":5},"file:///c%3A/Workspaces/Visual%20Studio%20Code/wuye/sp-ic-b/src/payment/payment.service.ts":{"language":"TypeScript","code":60,"comment":0,"blank":14},"file:///c%3A/Workspaces/Visual%20Studio%20Code/wuye/sp-ic-b/src/parking/parking.service.spec.ts":{"language":"TypeScript","code":14,"comment":0,"blank":5},"file:///c%3A/Workspaces/Visual%20Studio%20Code/wuye/sp-ic-b/src/outsider/outsider.module.ts":{"language":"TypeScript","code":11,"comment":0,"blank":2},"file:///c%3A/Workspaces/Visual%20Studio%20Code/wuye/sp-ic-b/src/payment/payment.service.spec.ts":{"language":"TypeScript","code":14,"comment":0,"blank":5},"file:///c%3A/Workspaces/Visual%20Studio%20Code/wuye/sp-ic-b/src/parking/parking.module.ts":{"language":"TypeScript","code":11,"comment":0,"blank":2},"file:///c%3A/Workspaces/Visual%20Studio%20Code/wuye/sp-ic-b/src/outsider/outsider.controller.ts":{"language":"TypeScript","code":55,"comment":0,"blank":10},"file:///c%3A/Workspaces/Visual%20Studio%20Code/wuye/sp-ic-b/src/payment/payment.module.ts":{"language":"TypeScript","code":11,"comment":0,"blank":2},"file:///c%3A/Workspaces/Visual%20Studio%20Code/wuye/sp-ic-b/src/parking/parking.controller.ts":{"language":"TypeScript","code":51,"comment":0,"blank":10},"file:///c%3A/Workspaces/Visual%20Studio%20Code/wuye/sp-ic-b/src/outsider/outsider.controller.spec.ts":{"language":"TypeScript","code":16,"comment":0,"blank":5},"file:///c%3A/Workspaces/Visual%20Studio%20Code/wuye/sp-ic-b/src/payment/payment.controller.ts":{"language":"TypeScript","code":48,"comment":0,"blank":10},"file:///c%3A/Workspaces/Visual%20Studio%20Code/wuye/sp-ic-b/src/payment/payment.controller.spec.ts":{"language":"TypeScript","code":16,"comment":0,"blank":5},"file:///c%3A/Workspaces/Visual%20Studio%20Code/wuye/sp-ic-b/src/parking/parking.controller.spec.ts":{"language":"TypeScript","code":16,"comment":0,"blank":5},"file:///c%3A/Workspaces/Visual%20Studio%20Code/wuye/sp-ic-b/src/post_collect/entities/post_collect.entity.ts":{"language":"TypeScript","code":14,"comment":0,"blank":5},"file:///c%3A/Workspaces/Visual%20Studio%20Code/wuye/sp-ic-b/src/outsider/entities/outsider.entity.ts":{"language":"TypeScript","code":20,"comment":0,"blank":8},"file:///c%3A/Workspaces/Visual%20Studio%20Code/wuye/sp-ic-b/src/parking/entities/parking.entity.ts":{"language":"TypeScript","code":16,"comment":0,"blank":6},"file:///c%3A/Workspaces/Visual%20Studio%20Code/wuye/sp-ic-b/src/post/post.service.ts":{"language":"TypeScript","code":81,"comment":0,"blank":15},"file:///c%3A/Workspaces/Visual%20Studio%20Code/wuye/sp-ic-b/src/post/post.service.spec.ts":{"language":"TypeScript","code":14,"comment":0,"blank":5},"file:///c%3A/Workspaces/Visual%20Studio%20Code/wuye/sp-ic-b/src/post_like/dtos/post_like.query.dto.ts":{"language":"TypeScript","code":6,"comment":0,"blank":1},"file:///c%3A/Workspaces/Visual%20Studio%20Code/wuye/sp-ic-b/src/post_like/dtos/post_like.delete.dto.ts":{"language":"TypeScript","code":6,"comment":0,"blank":1},"file:///c%3A/Workspaces/Visual%20Studio%20Code/wuye/sp-ic-b/src/post_like/dtos/post_like.create.dto.ts":{"language":"TypeScript","code":7,"comment":0,"blank":2},"file:///c%3A/Workspaces/Visual%20Studio%20Code/wuye/sp-ic-b/src/main.ts":{"language":"TypeScript","code":12,"comment":0,"blank":2},"file:///c%3A/Workspaces/Visual%20Studio%20Code/wuye/sp-ic-b/src/feedback/feedback.module.ts":{"language":"TypeScript","code":11,"comment":0,"blank":2},"file:///c%3A/Workspaces/Visual%20Studio%20Code/wuye/sp-ic-b/src/feedback/feedback.service.ts":{"language":"TypeScript","code":66,"comment":0,"blank":14},"file:///c%3A/Workspaces/Visual%20Studio%20Code/wuye/sp-ic-b/src/feedback/feedback.service.spec.ts":{"language":"TypeScript","code":14,"comment":0,"blank":5},"file:///c%3A/Workspaces/Visual%20Studio%20Code/wuye/sp-ic-b/src/goods/goods.service.ts":{"language":"TypeScript","code":75,"comment":1,"blank":14},"file:///c%3A/Workspaces/Visual%20Studio%20Code/wuye/sp-ic-b/src/log/log.module.ts":{"language":"TypeScript","code":11,"comment":0,"blank":2},"file:///c%3A/Workspaces/Visual%20Studio%20Code/wuye/sp-ic-b/src/feedback/feedback.controller.ts":{"language":"TypeScript","code":48,"comment":0,"blank":10},"file:///c%3A/Workspaces/Visual%20Studio%20Code/wuye/sp-ic-b/src/log/log.controller.ts":{"language":"TypeScript","code":34,"comment":0,"blank":6},"file:///c%3A/Workspaces/Visual%20Studio%20Code/wuye/sp-ic-b/src/feedback/feedback.controller.spec.ts":{"language":"TypeScript","code":16,"comment":0,"blank":5},"file:///c%3A/Workspaces/Visual%20Studio%20Code/wuye/sp-ic-b/src/goods/goods.service.spec.ts":{"language":"TypeScript","code":14,"comment":0,"blank":5},"file:///c%3A/Workspaces/Visual%20Studio%20Code/wuye/sp-ic-b/src/log/log.controller.spec.ts":{"language":"TypeScript","code":16,"comment":0,"blank":5},"file:///c%3A/Workspaces/Visual%20Studio%20Code/wuye/sp-ic-b/src/log/log.service.spec.ts":{"language":"TypeScript","code":14,"comment":0,"blank":5},"file:///c%3A/Workspaces/Visual%20Studio%20Code/wuye/sp-ic-b/src/log/log.service.ts":{"language":"TypeScript","code":47,"comment":0,"blank":8},"file:///c%3A/Workspaces/Visual%20Studio%20Code/wuye/sp-ic-b/src/goods/dtos/goods.create.dto.ts":{"language":"TypeScript","code":12,"comment":0,"blank":7},"file:///c%3A/Workspaces/Visual%20Studio%20Code/wuye/sp-ic-b/src/goods/goods.module.ts":{"language":"TypeScript","code":11,"comment":0,"blank":2},"file:///c%3A/Workspaces/Visual%20Studio%20Code/wuye/sp-ic-b/src/goods/goods.controller.ts":{"language":"TypeScript","code":57,"comment":0,"blank":10},"file:///c%3A/Workspaces/Visual%20Studio%20Code/wuye/sp-ic-b/src/parking/dtos/parking.query.dto.ts":{"language":"TypeScript","code":7,"comment":0,"blank":2},"file:///c%3A/Workspaces/Visual%20Studio%20Code/wuye/sp-ic-b/src/parking/dtos/parking.create.dto.ts":{"language":"TypeScript","code":7,"comment":0,"blank":2},"file:///c%3A/Workspaces/Visual%20Studio%20Code/wuye/sp-ic-b/src/parking/dtos/parking.delete.dto.ts":{"language":"TypeScript","code":6,"comment":0,"blank":1},"file:///c%3A/Workspaces/Visual%20Studio%20Code/wuye/sp-ic-b/src/goods/dtos/goods.update.dto.ts":{"language":"TypeScript","code":14,"comment":0,"blank":9},"file:///c%3A/Workspaces/Visual%20Studio%20Code/wuye/sp-ic-b/src/goods/dtos/goods.delete.dto.ts":{"language":"TypeScript","code":6,"comment":0,"blank":1},"file:///c%3A/Workspaces/Visual%20Studio%20Code/wuye/sp-ic-b/src/goods/dtos/goods.query.dto.ts":{"language":"TypeScript","code":7,"comment":0,"blank":2},"file:///c%3A/Workspaces/Visual%20Studio%20Code/wuye/sp-ic-b/src/goods/goods.controller.spec.ts":{"language":"TypeScript","code":16,"comment":0,"blank":5},"file:///c%3A/Workspaces/Visual%20Studio%20Code/wuye/sp-ic-b/src/feedback/dtos/feedback.create.dto.ts":{"language":"TypeScript","code":9,"comment":0,"blank":4},"file:///c%3A/Workspaces/Visual%20Studio%20Code/wuye/sp-ic-b/src/log/entities/log.entity.ts":{"language":"TypeScript","code":22,"comment":0,"blank":9},"file:///c%3A/Workspaces/Visual%20Studio%20Code/wuye/sp-ic-b/src/feedback/dtos/feedback.delete.dto.ts":{"language":"TypeScript","code":6,"comment":0,"blank":1},"file:///c%3A/Workspaces/Visual%20Studio%20Code/wuye/sp-ic-b/src/feedback/entities/feedback.entity.ts":{"language":"TypeScript","code":22,"comment":0,"blank":9},"file:///c%3A/Workspaces/Visual%20Studio%20Code/wuye/sp-ic-b/src/log/dtos/log.query.dto.ts":{"language":"TypeScript","code":10,"comment":0,"blank":4},"file:///c%3A/Workspaces/Visual%20Studio%20Code/wuye/sp-ic-b/src/parking/dtos/parking.update.dto.ts":{"language":"TypeScript","code":9,"comment":0,"blank":4},"file:///c%3A/Workspaces/Visual%20Studio%20Code/wuye/sp-ic-b/src/payment/dtos/payment.update.dto.ts":{"language":"TypeScript","code":6,"comment":0,"blank":1},"file:///c%3A/Workspaces/Visual%20Studio%20Code/wuye/sp-ic-b/src/feedback/dtos/feedback.query.dto.ts":{"language":"TypeScript","code":7,"comment":0,"blank":2},"file:///c%3A/Workspaces/Visual%20Studio%20Code/wuye/sp-ic-b/src/payment/dtos/payment.query.dto.ts":{"language":"TypeScript","code":7,"comment":0,"blank":2},"file:///c%3A/Workspaces/Visual%20Studio%20Code/wuye/sp-ic-b/src/payment/dtos/payment.create.dto.ts":{"language":"TypeScript","code":10,"comment":0,"blank":5},"file:///c%3A/Workspaces/Visual%20Studio%20Code/wuye/sp-ic-b/src/payment/dtos/payment.delete.dto.ts":{"language":"TypeScript","code":6,"comment":0,"blank":1},"file:///c%3A/Workspaces/Visual%20Studio%20Code/wuye/sp-ic-b/src/outsider/dtos/outsider.update.dto.ts":{"language":"TypeScript","code":10,"comment":0,"blank":5},"file:///c%3A/Workspaces/Visual%20Studio%20Code/wuye/sp-ic-b/src/outsider/dtos/outsider.query.dto.ts":{"language":"TypeScript","code":7,"comment":0,"blank":2},"file:///c%3A/Workspaces/Visual%20Studio%20Code/wuye/sp-ic-b/src/log/dtos/log.create.dto.ts":{"language":"TypeScript","code":7,"comment":0,"blank":2},"file:///c%3A/Workspaces/Visual%20Studio%20Code/wuye/sp-ic-b/src/outsider/dtos/outsider.delete.dto.ts":{"language":"TypeScript","code":6,"comment":0,"blank":1},"file:///c%3A/Workspaces/Visual%20Studio%20Code/wuye/sp-ic-b/src/outsider/dtos/outsider.create.dto.ts":{"language":"TypeScript","code":9,"comment":0,"blank":4},"file:///c%3A/Workspaces/Visual%20Studio%20Code/wuye/sp-ic-b/src/feedback/dtos/feedback.update.dto.ts":{"language":"TypeScript","code":7,"comment":0,"blank":2},"file:///c%3A/Workspaces/Visual%20Studio%20Code/wuye/sp-ic-b/src/goods/entities/goods.entity.ts":{"language":"TypeScript","code":29,"comment":0,"blank":12},"file:///c%3A/Workspaces/Visual%20Studio%20Code/wuye/sp-ic-b/src/app.service.ts":{"language":"TypeScript","code":7,"comment":0,"blank":2},"file:///c%3A/Workspaces/Visual%20Studio%20Code/wuye/sp-ic-b/src/app.module.ts":{"language":"TypeScript","code":62,"comment":0,"blank":2},"file:///c%3A/Workspaces/Visual%20Studio%20Code/wuye/sp-ic-b/src/app.controller.ts":{"language":"TypeScript","code":10,"comment":0,"blank":3},"file:///c%3A/Workspaces/Visual%20Studio%20Code/wuye/sp-ic-b/src/app.controller.spec.ts":{"language":"TypeScript","code":18,"comment":0,"blank":5},"file:///c%3A/Workspaces/Visual%20Studio%20Code/wuye/sp-ic-b/src/.tools/string.tool.ts":{"language":"TypeScript","code":5,"comment":0,"blank":0},"file:///c%3A/Workspaces/Visual%20Studio%20Code/wuye/sp-ic-b/src/post_collect/dtos/post_collect.delete.dto.ts":{"language":"TypeScript","code":7,"comment":0,"blank":2},"file:///c%3A/Workspaces/Visual%20Studio%20Code/wuye/sp-ic-b/src/.dtos/dto.ts":{"language":"TypeScript","code":4,"comment":0,"blank":1},"file:///c%3A/Workspaces/Visual%20Studio%20Code/wuye/sp-ic-b/src/post_collect/dtos/post_collect.query.dto.ts":{"language":"TypeScript","code":7,"comment":0,"blank":2},"file:///c%3A/Workspaces/Visual%20Studio%20Code/wuye/sp-ic-b/src/.tools/password.tool.ts":{"language":"TypeScript","code":14,"comment":0,"blank":4},"file:///c%3A/Workspaces/Visual%20Studio%20Code/wuye/sp-ic-b/src/.tools/object.tool.ts":{"language":"TypeScript","code":6,"comment":0,"blank":1},"file:///c%3A/Workspaces/Visual%20Studio%20Code/wuye/sp-ic-b/src/post_collect/dtos/post_collect.create.dto.ts":{"language":"TypeScript","code":7,"comment":0,"blank":2},"file:///c%3A/Workspaces/Visual%20Studio%20Code/wuye/sp-ic-b/src/.tools/number.tool.ts":{"language":"TypeScript","code":14,"comment":0,"blank":3},"file:///c%3A/Workspaces/Visual%20Studio%20Code/wuye/sp-ic-b/src/.dtos/result.ts":{"language":"TypeScript","code":20,"comment":0,"blank":7},"file:///c%3A/Workspaces/Visual%20Studio%20Code/wuye/sp-ic-b/src/bill/bill.service.ts":{"language":"TypeScript","code":75,"comment":0,"blank":11},"file:///c%3A/Workspaces/Visual%20Studio%20Code/wuye/sp-ic-b/src/.tools/boolean.tool.ts":{"language":"TypeScript","code":5,"comment":0,"blank":0},"file:///c%3A/Workspaces/Visual%20Studio%20Code/wuye/sp-ic-b/src/post_collect/dtos/post_collect.query_list.dto.ts":{"language":"TypeScript","code":7,"comment":0,"blank":2},"file:///c%3A/Workspaces/Visual%20Studio%20Code/wuye/sp-ic-b/src/.tools/time.tool.ts":{"language":"TypeScript","code":5,"comment":0,"blank":0},"file:///c%3A/Workspaces/Visual%20Studio%20Code/wuye/sp-ic-b/src/bill/bill.module.ts":{"language":"TypeScript","code":11,"comment":0,"blank":2},"file:///c%3A/Workspaces/Visual%20Studio%20Code/wuye/sp-ic-b/src/bill/bill.service.spec.ts":{"language":"TypeScript","code":14,"comment":0,"blank":5},"file:///c%3A/Workspaces/Visual%20Studio%20Code/wuye/sp-ic-b/src/attend/attend.service.ts":{"language":"TypeScript","code":66,"comment":0,"blank":11},"file:///c%3A/Workspaces/Visual%20Studio%20Code/wuye/sp-ic-b/src/attend/attend.service.spec.ts":{"language":"TypeScript","code":14,"comment":0,"blank":5},"file:///c%3A/Workspaces/Visual%20Studio%20Code/wuye/sp-ic-b/src/attend/attend.module.ts":{"language":"TypeScript","code":11,"comment":0,"blank":2},"file:///c%3A/Workspaces/Visual%20Studio%20Code/wuye/sp-ic-b/src/bill/bill.controller.ts":{"language":"TypeScript","code":40,"comment":0,"blank":8},"file:///c%3A/Workspaces/Visual%20Studio%20Code/wuye/sp-ic-b/src/attend/attend.controller.ts":{"language":"TypeScript","code":45,"comment":0,"blank":9},"file:///c%3A/Workspaces/Visual%20Studio%20Code/wuye/sp-ic-b/src/attend/attend.controller.spec.ts":{"language":"TypeScript","code":16,"comment":0,"blank":5},"file:///c%3A/Workspaces/Visual%20Studio%20Code/wuye/sp-ic-b/src/bill/bill.controller.spec.ts":{"language":"TypeScript","code":16,"comment":0,"blank":5},"file:///c%3A/Workspaces/Visual%20Studio%20Code/wuye/sp-ic-b/nest-cli.json":{"language":"JSON","code":8,"comment":0,"blank":1},"file:///c%3A/Workspaces/Visual%20Studio%20Code/wuye/sp-ic-b/src/.const/msg.const.ts":{"language":"TypeScript","code":175,"comment":0,"blank":132},"file:///c%3A/Workspaces/Visual%20Studio%20Code/wuye/sp-ic-b/src/.const/num.const.ts":{"language":"TypeScript","code":5,"comment":0,"blank":2},"file:///c%3A/Workspaces/Visual%20Studio%20Code/wuye/sp-ic-b/src/.const/var.const.ts":{"language":"TypeScript","code":4,"comment":0,"blank":0},"file:///c%3A/Workspaces/Visual%20Studio%20Code/wuye/sp-ic-b/src/attend/dtos/attend.update.dto.ts":{"language":"TypeScript","code":7,"comment":0,"blank":2},"file:///c%3A/Workspaces/Visual%20Studio%20Code/wuye/sp-ic-b/src/attend/dtos/attend.query.dto.ts":{"language":"TypeScript","code":9,"comment":0,"blank":4},"file:///c%3A/Workspaces/Visual%20Studio%20Code/wuye/sp-ic-b/src/attend/dtos/attend.create.dto.ts":{"language":"TypeScript","code":7,"comment":0,"blank":2},"file:///c%3A/Workspaces/Visual%20Studio%20Code/wuye/sp-ic-b/src/.const/init.const.ts":{"language":"TypeScript","code":3,"comment":0,"blank":0},"file:///c%3A/Workspaces/Visual%20Studio%20Code/wuye/sp-ic-b/src/activity/activity.service.ts":{"language":"TypeScript","code":54,"comment":0,"blank":14},"file:///c%3A/Workspaces/Visual%20Studio%20Code/wuye/sp-ic-b/src/activity/activity.service.spec.ts":{"language":"TypeScript","code":14,"comment":0,"blank":5},"file:///c%3A/Workspaces/Visual%20Studio%20Code/wuye/sp-ic-b/src/bill/entities/bill.entity.ts":{"language":"TypeScript","code":24,"comment":0,"blank":10},"file:///c%3A/Workspaces/Visual%20Studio%20Code/wuye/sp-ic-b/src/activity/activity.module.ts":{"language":"TypeScript","code":11,"comment":0,"blank":2},"file:///c%3A/Workspaces/Visual%20Studio%20Code/wuye/sp-ic-b/src/activity/activity.controller.ts":{"language":"TypeScript","code":61,"comment":0,"blank":10},"file:///c%3A/Workspaces/Visual%20Studio%20Code/wuye/sp-ic-b/src/attend/entities/attend.entity.ts":{"language":"TypeScript","code":16,"comment":0,"blank":6},"file:///c%3A/Workspaces/Visual%20Studio%20Code/wuye/sp-ic-b/src/activity/activity.controller.spec.ts":{"language":"TypeScript","code":16,"comment":0,"blank":5},"file:///c%3A/Workspaces/Visual%20Studio%20Code/wuye/sp-ic-b/src/activity/dtos/activity.update.dto.ts":{"language":"TypeScript","code":14,"comment":0,"blank":9},"file:///c%3A/Workspaces/Visual%20Studio%20Code/wuye/sp-ic-b/src/activity/dtos/activity.query.dto.ts":{"language":"TypeScript","code":8,"comment":0,"blank":3},"file:///c%3A/Workspaces/Visual%20Studio%20Code/wuye/sp-ic-b/src/bill/dtos/bill.update.dto.ts":{"language":"TypeScript","code":7,"comment":0,"blank":2},"file:///c%3A/Workspaces/Visual%20Studio%20Code/wuye/sp-ic-b/src/bill/dtos/bill.query.dto.ts":{"language":"TypeScript","code":8,"comment":0,"blank":3},"file:///c%3A/Workspaces/Visual%20Studio%20Code/wuye/sp-ic-b/Dockerfile":{"language":"Docker","code":8,"comment":5,"blank":9},"file:///c%3A/Workspaces/Visual%20Studio%20Code/wuye/sp-ic-b/src/.sql/init.sql":{"language":"SQL","code":20,"comment":10,"blank":9},"file:///c%3A/Workspaces/Visual%20Studio%20Code/wuye/sp-ic-b/.github/workflows/learn-github-actions.yml":{"language":"YAML","code":32,"comment":0,"blank":7},"file:///c%3A/Workspaces/Visual%20Studio%20Code/wuye/sp-ic-b/src/bill/dtos/bill.delete.dto.ts":{"language":"TypeScript","code":6,"comment":0,"blank":1},"file:///c%3A/Workspaces/Visual%20Studio%20Code/wuye/sp-ic-b/src/activity/dtos/activity.delete.dto.ts":{"language":"TypeScript","code":6,"comment":0,"blank":2},"file:///c%3A/Workspaces/Visual%20Studio%20Code/wuye/sp-ic-b/src/activity/dtos/activity.create.dto.ts":{"language":"TypeScript","code":13,"comment":0,"blank":9},"file:///c%3A/Workspaces/Visual%20Studio%20Code/wuye/sp-ic-b/src/activity/entities/activity.entity.ts":{"language":"TypeScript","code":28,"comment":0,"blank":12},"file:///c%3A/Workspaces/Visual%20Studio%20Code/wuye/sp-ic-b/.prettierrc":{"language":"JSON","code":4,"comment":0,"blank":0}}